ondivi/__init__.py
ondivi/_internal/__init__.py
ondivi/_internal/define_changed_lines.py
ondivi/_internal/filter_out_violations.py
ondivi/_internal/ondivi_types.py
ondivi/entry.py
ondivi-0.7.3.dist-info/METADATA
ondivi-0.7.3.dist-info/WHEEL
ondivi-0.7.3.dist-info/entry_points.txt
ondivi-0.7.3.dist-info/licenses/LICENSE
ondivi-0.7.3.dist-info/RECORD
