Metadata-Version: 2.4
Name: ondivi
Version: 0.7.3
Summary: 
License-File: LICENSE
Author: Almaz Ilaletdinov
Author-email: a.ilaletdinov@yandex.ru
Requires-Python: >=3.10,<4.0
Classifier: Programming Language :: Python :: 3
Classifier: Programming Language :: Python :: 3.10
Classifier: Programming Language :: Python :: 3.11
Classifier: Programming Language :: Python :: 3.12
Classifier: Programming Language :: Python :: 3.13
Classifier: Programming Language :: Python :: 3.14
Requires-Dist: click (>=0.2)
Requires-Dist: gitpython (>=2.1.15)
Requires-Dist: parse (>=1.4,<2.0)
